LICENSE
MANIFEST.in
README.rst
setup.py
codingsohodemo/__init__.py
codingsohodemo/admin.py
codingsohodemo/apps.py
codingsohodemo/models.py
codingsohodemo/tests.py
codingsohodemo/urls.py
codingsohodemo/views.py
codingsohodemo/migrations/__init__.py
codingsohodemo/static/codingsohodemo/css/pgwslideshow.min.css
codingsohodemo/static/codingsohodemo/js/pgwslideshow.min.js
codingsohodemo/static/js/jquery.min.js
codingsohodemo/templates/base_site.html
codingsohodemo/templates/codingsohodemo/pgwshow.html
django_codingsohodemo.egg-info/PKG-INFO
django_codingsohodemo.egg-info/SOURCES.txt
django_codingsohodemo.egg-info/dependency_links.txt
django_codingsohodemo.egg-info/top_level.txt
docs/blank.txt