Metadata-Version: 1.1
Name: django-codingsohodemo
Version: 1.1
Summary: django-codingsohodmeo project is demo application  for codingsoho
Home-page: https://www.codingsoho.com/
Author: Horde Chief
Author-email: hordechief@qq.com
License: BSD License
Platform: UNKNOWN
Classifier: Environment :: Web Environment
Classifier: Framework :: Django
Classifier: Framework :: Django :: 1.11
Classifier: Intended Audience :: Developers
Classifier: License :: OSI Approved :: BSD License
Classifier: Operating System :: OS Independent
Classifier: Programming Language :: Python
Classifier: Programming Language :: Python :: 2
Classifier: Programming Language :: Python :: 2.7
Classifier: Topic :: Internet :: WWW/HTTP
Classifier: Topic :: Internet :: WWW/HTTP :: Dynamic Content
